CHANGELOG
INSTALL
LICENSE
MANIFEST.in
README
setup.py
MadeiraCloud.egg-info/PKG-INFO
MadeiraCloud.egg-info/SOURCES.txt
MadeiraCloud.egg-info/dependency_links.txt
MadeiraCloud.egg-info/requires.txt
MadeiraCloud.egg-info/top_level.txt
bin/madeira.py
madeiracloud/Health.py
madeiracloud/Log.py
madeiracloud/RTimer.py
madeiracloud/Task.py
madeiracloud/Watcher.py
madeiracloud/__init__.py
script/centos.sh
script/debian.sh
script/fedora.sh
script/opensuse.sh
script/others.sh
script/redhat.sh
script/suse.sh
script/ubuntu.sh
script/upstart.sh