Metadata-Version: 1.0
Name: MadeiraCloud
Version: 1.0.0
Summary: MadeiraCloud Agent
Home-page: http://www.madeiracloud.com
Author: dev@madeiracloud.com
Author-email: support@madeiracloud.com
License: GPL
Keywords: MadeiraCloud AWS
Platform: UNKNOWN
Classifier: Development Status :: 4 - Beta
Classifier: Environment :: No Input/Output (Daemon)
Classifier: Intended Audience :: Developers
Classifier: Intended Audience :: System Administrators
Classifier: License :: OSI Approved :: GNU General Public License (GPL)
Classifier: Natural Language :: English
Classifier: Operating System :: POSIX :: Linux
Classifier: Programming Language :: Python :: 2.4
Classifier: Programming Language :: Python :: 2.5
Classifier: Programming Language :: Python :: 2.6
Classifier: Programming Language :: Python :: 2.7
Classifier: Topic :: System :: Networking :: Monitoring
Classifier: Topic :: System :: Systems Administration
